Metadata-Version: 2.4
Name: compoundwidgets
Version: 0.5.12
Summary: Compound TTK Widgets with ttkbootstrap
Home-page: https://github.com/AndreMariano100/CompoundWidgets.git
Author: Andre Mariano
Author-email: andremariano100@gmail.com
License: MIT
Classifier: Programming Language :: Python :: 3
License-File: LICENSE.txt
Requires-Dist: ttkbootstrap
Requires-Dist: Pillow
Dynamic: author
Dynamic: author-email
Dynamic: classifier
Dynamic: description
Dynamic: description-content-type
Dynamic: home-page
Dynamic: license
Dynamic: license-file
Dynamic: requires-dist
Dynamic: summary
